_pi_heif.cpython-312-aarch64-linux-musl.so
pi_heif/HeifImagePlugin.py
pi_heif/__init__.py
pi_heif/_deffered_error.py
pi_heif/_lib_info.py
pi_heif/_version.py
pi_heif/as_plugin.py
pi_heif/constants.py
pi_heif/heif.py
pi_heif/misc.py
pi_heif/options.py
pi_heif.libs/libde265-ae96ab7c.so
pi_heif.libs/libgcc_s-2d945d6c.so.1
pi_heif.libs/libheif-a91d1554.so.1.20.2
pi_heif.libs/libstdc++-85f2cd6d.so.6.0.33
pi_heif-1.1.1.dist-info/METADATA
pi_heif-1.1.1.dist-info/WHEEL
pi_heif-1.1.1.dist-info/top_level.txt
pi_heif-1.1.1.dist-info/zip-safe
pi_heif-1.1.1.dist-info/RECORD
pi_heif-1.1.1.dist-info/licenses/LICENSE.txt
pi_heif-1.1.1.dist-info/licenses/LICENSES_bundled.txt
